huaweicloudsdkcodeartsinspector/__init__.py
huaweicloudsdkcodeartsinspector/v2/__init__.py
huaweicloudsdkcodeartsinspector/v2/codeartsinspector_async_client.py
huaweicloudsdkcodeartsinspector/v2/codeartsinspector_client.py
huaweicloudsdkcodeartsinspector/v2/model/__init__.py
huaweicloudsdkcodeartsinspector/v2/model/create_cbc_order_request_body.py
huaweicloudsdkcodeartsinspector/v2/model/create_purchase_order_request.py
huaweicloudsdkcodeartsinspector/v2/model/create_purchase_order_response.py
huaweicloudsdkcodeartsinspector/v2/model/product_info.py
huaweicloudsdkcodeartsinspector/v2/model/update_cbc_order_request_body.py
huaweicloudsdkcodeartsinspector/v2/model/update_cbc_order_request_body_product_info.py
huaweicloudsdkcodeartsinspector/v2/model/update_purchase_order_request.py
huaweicloudsdkcodeartsinspector/v2/model/update_purchase_order_response.py
huaweicloudsdkcodeartsinspector/v2/region/__init__.py
huaweicloudsdkcodeartsinspector/v2/region/codeartsinspector_region.py
huaweicloudsdkcodeartsinspector/v3/__init__.py
huaweicloudsdkcodeartsinspector/v3/codeartsinspector_async_client.py
huaweicloudsdkcodeartsinspector/v3/codeartsinspector_client.py
huaweicloudsdkcodeartsinspector/v3/model/__init__.py
huaweicloudsdkcodeartsinspector/v3/model/add_group_request.py
huaweicloudsdkcodeartsinspector/v3/model/add_group_request_body.py
huaweicloudsdkcodeartsinspector/v3/model/add_group_response.py
huaweicloudsdkcodeartsinspector/v3/model/authorize_domains_request.py
huaweicloudsdkcodeartsinspector/v3/model/authorize_domains_request_body.py
huaweicloudsdkcodeartsinspector/v3/model/authorize_domains_response.py
huaweicloudsdkcodeartsinspector/v3/model/batch_create_hosts_request.py
huaweicloudsdkcodeartsinspector/v3/model/batch_create_hosts_request_body.py
huaweicloudsdkcodeartsinspector/v3/model/batch_create_hosts_response.py
huaweicloudsdkcodeartsinspector/v3/model/batch_start_host_tasks_request.py
huaweicloudsdkcodeartsinspector-3.1.184.dist-info/METADATA
huaweicloudsdkcodeartsinspector-3.1.184.dist-info/WHEEL
huaweicloudsdkcodeartsinspector-3.1.184.dist-info/licenses/LICENSE
huaweicloudsdkcodeartsinspector-3.1.184.dist-info/RECORD
